{
  "theme": "system",
  "translucency": false,
  "interfaceFontFamily": "Arial",
  "textFontFamily": "",
  "baseFontSize": 16,
  "enabledCssSnippets": [
    "自定义 微调",
    "LazyCoder",
    "边距背景调整",
    "Tab 栏优化",
    "表格体验优化",
    "fengstats",
    "AnuExtendTheme",
    "文内搜索优化",
    "目录文件图标",
    "滚动条",
    "Codeblock",
    "表格行号",
    "Basic",
    "LitsTask",
    "LitstTask",
    "ListTask",
    "X-Vim",
    "X-Memos",
    "X-Calendar",
    "X-AnuExtendTheme",
    "FolderAndFile",
    "List",
    "Picture",
    "Search",
    "Tab",
    "Title",
    "X-CheckList",
    "Quote",
    "CodeBlock",
    "Editor",
    "Background"
  ],
  "cssTheme": "AnuPpuccin",
  "accentColor": "",
  "showViewHeader": true,
  "nativeMenus": true,
  "monospaceFontFamily": "Input Mono Freeze",
  "baseFontSizeAction": false
}